{"scene_name": "47204840", "regions": {"0": {"the sofa that is in between both of the tables": [{"target_index": "0", "anchor1_index": "1", "anchor2_index": "2", "target_class": "sofa", "anchor1_class": "table", "anchor2_class": "table", "target_position": [-0.8847286519782817, 2.820139867313476, -0.8151715099811554], "anchor1_position": [-0.628616208890724, 1.2396757955503994, -0.9589380025863647], "anchor2_position": [-0.3500412798670293, 4.194660104284085, -0.8701274991035461], "target_colors": ["white", "white", "white"], "anchor1_colors": ["white", "white", "white"], "anchor2_colors": ["white", "white", "white"], "target_size": 1.3048886845010141, "anchor1_size": 0.05774846750669003, "anchor2_size": 0.25376759151187633, "target_color_used": false, "target_size_used": false, "anchor1_color_used": false, "anchor1_size_used": false, "anchor2_color_used": false, "anchor2_size_used": false, "distractor_ids": [], "relation": "between", "relation_type": "ternary"}], "the fireplace that is in between both of the tables": [{"target_index": "3", "anchor1_index": "2", "anchor2_index": "4", "target_class": "fireplace", "anchor1_class": "table", "anchor2_class": "table", "target_position": [1.0792443169216395, 3.7453244376919157, -0.6639344990253448], "anchor1_position": [-0.3500412798670293, 4.194660104284085, -0.8701274991035461], "anchor2_position": [2.3916712154017836, 3.666921674464924, -0.9619214832782745], "target_colors": ["white", "black", "white"], "anchor1_colors": ["white", "white", "white"], "anchor2_colors": ["black", "white", "N/A"], "target_size": 0.6292661753359982, "anchor1_size": 0.25376759151187633, "anchor2_size": 0.15684705036934382, "target_color_used": false, "target_size_used": false, "anchor1_color_used": false, "anchor1_size_used": false, "anchor2_color_used": false, "anchor2_size_used": false, "distractor_ids": [], "relation": "between", "relation_type": "ternary"}], "the fireplace that is in between the sofa and the table": [{"target_index": "3", "anchor1_index": "0", "anchor2_index": "4", "target_class": "fireplace", "anchor1_class": "sofa", "anchor2_class": "table", "target_position": [1.0792443169216395, 3.7453244376919157, -0.6639344990253448], "anchor1_position": [-0.8847286519782817, 2.820139867313476, -0.8151715099811554], "anchor2_position": [2.3916712154017836, 3.666921674464924, -0.9619214832782745], "target_colors": ["white", "black", "white"], "anchor1_colors": ["white", "white", "white"], "anchor2_colors": ["black", "white", "N/A"], "target_size": 0.6292661753359982, "anchor1_size": 1.3048886845010141, "anchor2_size": 0.15684705036934382, "target_color_used": false, "target_size_used": false, "anchor1_color_used": false, "anchor1_size_used": false, "anchor2_color_used": false, "anchor2_size_used": false, "distractor_ids": [], "relation": "between", "relation_type": "ternary"}], "the fireplace that is in between the table and the television": [{"target_index": "3", "anchor1_index": "2", "anchor2_index": "5", "target_class": "fireplace", "anchor1_class": "table", "anchor2_class": "television", "target_position": [1.0792443169216395, 3.7453244376919157, -0.6639344990253448], "anchor1_position": [-0.3500412798670293, 4.194660104284085, -0.8701274991035461], "anchor2_position": [2.4017462182100293, 3.6206627919874306, -0.45068351179361343], "target_colors": ["white", "black", "white"], "anchor1_colors": ["white", "white", "white"], "anchor2_colors": ["black", "white", "N/A"], "target_size": 0.6292661753359982, "anchor1_size": 0.25376759151187633, "anchor2_size": 0.024298726093454417, "target_color_used": false, "target_size_used": false, "anchor1_color_used": false, "anchor1_size_used": false, "anchor2_color_used": false, "anchor2_size_used": false, "distractor_ids": [], "relation": "between", "relation_type": "ternary"}], "the sofa that is closest to the small table": [{"target_index": "0", "anchor_index": "1", "target_class": "sofa", "anchor_class": "table", "target_position": [-0.8847286519782817, 2.820139867313476, -0.8151715099811554], "anchor_position": [-0.628616208890724, 1.2396757955503994, -0.9589380025863647], "target_colors": ["white", "white", "white"], "anchor_colors": ["white", "white", "white"], "target_size": 1.3048886845010141, "anchor_size": 0.05774846750669003, "target_color_used": false, "target_size_used": true, "anchor_color_used": false, "anchor_size_used": true, "distractor_ids": ["6"], "relation": "closest", "relation_type": "ordered"}], "the sofa that is second closest to the small table": [{"target_index": "6", "anchor_index": "1", "target_class": "sofa", "anchor_class": "table", "target_position": [1.646969569725383, 1.4343831838574637, -0.8058465123176575], "anchor_position": [-0.628616208890724, 1.2396757955503994, -0.9589380025863647], "target_colors": ["white", "white", "white"], "anchor_colors": ["white", "white", "white"], "target_size": 1.558315309492041, "anchor_size": 0.05774846750669003, "target_color_used": false, "target_size_used": true, "anchor_color_used": false, "anchor_size_used": true, "distractor_ids": ["0"], "relation": "closest", "relation_type": "ordered"}], "the sofa that is closest to the big table": [{"target_index": "0", "anchor_index": "2", "target_class": "sofa", "anchor_class": "table", "target_position": [-0.8847286519782817, 2.820139867313476, -0.8151715099811554], "anchor_position": [-0.3500412798670293, 4.194660104284085, -0.8701274991035461], "target_colors": ["white", "white", "white"], "anchor_colors": ["white", "white", "white"], "target_size": 1.3048886845010141, "anchor_size": 0.25376759151187633, "target_color_used": false, "target_size_used": true, "anchor_color_used": false, "anchor_size_used": true, "distractor_ids": ["6"], "relation": "closest", "relation_type": "ordered"}], "the sofa that is second closest to the big table": [{"target_index": "6", "anchor_index": "2", "target_class": "sofa", "anchor_class": "table", "target_position": [1.646969569725383, 1.4343831838574637, -0.8058465123176575], "anchor_position": [-0.3500412798670293, 4.194660104284085, -0.8701274991035461], "target_colors": ["white", "white", "white"], "anchor_colors": ["white", "white", "white"], "target_size": 1.558315309492041, "anchor_size": 0.25376759151187633, "target_color_used": false, "target_size_used": true, "anchor_color_used": false, "anchor_size_used": true, "distractor_ids": ["0"], "relation": "closest", "relation_type": "ordered"}], "the sofa that is closest to the black table": [{"target_index": "6", "anchor_index": "4", "target_class": "sofa", "anchor_class": "table", "target_position": [1.646969569725383, 1.4343831838574637, -0.8058465123176575], "anchor_position": [2.3916712154017836, 3.666921674464924, -0.9619214832782745], "target_colors": ["white", "white", "white"], "anchor_colors": ["black", "white", "N/A"], "target_size": 1.558315309492041, "anchor_size": 0.15684705036934382, "target_color_used": true, "target_size_used": false, "anchor_color_used": true, "anchor_size_used": false, "distractor_ids": ["0"], "relation": "closest", "relation_type": "ordered"}], "the sofa that is second closest to the black table": [{"target_index": "0", "anchor_index": "4", "target_class": "sofa", "anchor_class": "table", "target_position": [-0.8847286519782817, 2.820139867313476, -0.8151715099811554], "anchor_position": [2.3916712154017836, 3.666921674464924, -0.9619214832782745], "target_colors": ["white", "white", "white"], "anchor_colors": ["black", "white", "N/A"], "target_size": 1.3048886845010141, "anchor_size": 0.15684705036934382, "target_color_used": true, "target_size_used": false, "anchor_color_used": true, "anchor_size_used": false, "distractor_ids": ["6"], "relation": "closest", "relation_type": "ordered"}], "the table that is closest to the fireplace": [{"target_index": "4", "anchor_index": "3", "target_class": "table", "anchor_class": "fireplace", "target_position": [2.3916712154017836, 3.666921674464924, -0.9619214832782745], "anchor_position": [1.0792443169216395, 3.7453244376919157, -0.6639344990253448], "target_colors": ["black", "white", "N/A"], "anchor_colors": ["white", "black", "white"], "target_size": 0.15684705036934382, "anchor_size": 0.6292661753359982, "target_color_used": false, "target_size_used": false, "anchor_color_used": false, "anchor_size_used": false, "distractor_ids": ["2", "1"], "relation": "closest", "relation_type": "ordered"}], "the table that is second closest to the fireplace": [{"target_index": "2", "anchor_index": "3", "target_class": "table", "anchor_class": "fireplace", "target_position": [-0.3500412798670293, 4.194660104284085, -0.8701274991035461], "anchor_position": [1.0792443169216395, 3.7453244376919157, -0.6639344990253448], "target_colors": ["white", "white", "white"], "anchor_colors": ["white", "black", "white"], "target_size": 0.25376759151187633, "anchor_size": 0.6292661753359982, "target_color_used": false, "target_size_used": false, "anchor_color_used": false, "anchor_size_used": false, "distractor_ids": ["4", "1"], "relation": "closest", "relation_type": "ordered"}], "the table that is third closest to the fireplace": [{"target_index": "1", "anchor_index": "3", "target_class": "table", "anchor_class": "fireplace", "target_position": [-0.628616208890724, 1.2396757955503994, -0.9589380025863647], "anchor_position": [1.0792443169216395, 3.7453244376919157, -0.6639344990253448], "target_colors": ["white", "white", "white"], "anchor_colors": ["white", "black", "white"], "target_size": 0.05774846750669003, "anchor_size": 0.6292661753359982, "target_color_used": false, "target_size_used": false, "anchor_color_used": false, "anchor_size_used": false, "distractor_ids": ["4", "2"], "relation": "closest", "relation_type": "ordered"}], "the sofa that is closest to the fireplace": [{"target_index": "0", "anchor_index": "3", "target_class": "sofa", "anchor_class": "fireplace", "target_position": [-0.8847286519782817, 2.820139867313476, -0.8151715099811554], "anchor_position": [1.0792443169216395, 3.7453244376919157, -0.6639344990253448], "target_colors": ["white", "white", "white"], "anchor_colors": ["white", "black", "white"], "target_size": 1.3048886845010141, "anchor_size": 0.6292661753359982, "target_color_used": false, "target_size_used": false, "anchor_color_used": false, "anchor_size_used": false, "distractor_ids": ["6"], "relation": "closest", "relation_type": "ordered"}], "the sofa that is second closest to the fireplace": [{"target_index": "6", "anchor_index": "3", "target_class": "sofa", "anchor_class": "fireplace", "target_position": [1.646969569725383, 1.4343831838574637, -0.8058465123176575], "anchor_position": [1.0792443169216395, 3.7453244376919157, -0.6639344990253448], "target_colors": ["white", "white", "white"], "anchor_colors": ["white", "black", "white"], "target_size": 1.558315309492041, "anchor_size": 0.6292661753359982, "target_color_used": false, "target_size_used": false, "anchor_color_used": false, "anchor_size_used": false, "distractor_ids": ["0"], "relation": "closest", "relation_type": "ordered"}], "the table that is closest to the television": [{"target_index": "4", "anchor_index": "5", "target_class": "table", "anchor_class": "television", "target_position": [2.3916712154017836, 3.666921674464924, -0.9619214832782745], "anchor_position": [2.4017462182100293, 3.6206627919874306, -0.45068351179361343], "target_colors": ["black", "white", "N/A"], "anchor_colors": ["black", "white", "N/A"], "target_size": 0.15684705036934382, "anchor_size": 0.024298726093454417, "target_color_used": false, "target_size_used": false, "anchor_color_used": false, "anchor_size_used": false, "distractor_ids": ["2", "1"], "relation": "closest", "relation_type": "ordered"}], "the table that is second closest to the television": [{"target_index": "2", "anchor_index": "5", "target_class": "table", "anchor_class": "television", "target_position": [-0.3500412798670293, 4.194660104284085, -0.8701274991035461], "anchor_position": [2.4017462182100293, 3.6206627919874306, -0.45068351179361343], "target_colors": ["white", "white", "white"], "anchor_colors": ["black", "white", "N/A"], "target_size": 0.25376759151187633, "anchor_size": 0.024298726093454417, "target_color_used": false, "target_size_used": false, "anchor_color_used": false, "anchor_size_used": false, "distractor_ids": ["4", "1"], "relation": "closest", "relation_type": "ordered"}], "the table that is third closest to the television": [{"target_index": "1", "anchor_index": "5", "target_class": "table", "anchor_class": "television", "target_position": [-0.628616208890724, 1.2396757955503994, -0.9589380025863647], "anchor_position": [2.4017462182100293, 3.6206627919874306, -0.45068351179361343], "target_colors": ["white", "white", "white"], "anchor_colors": ["black", "white", "N/A"], "target_size": 0.05774846750669003, "anchor_size": 0.024298726093454417, "target_color_used": false, "target_size_used": false, "anchor_color_used": false, "anchor_size_used": false, "distractor_ids": ["4", "2"], "relation": "closest", "relation_type": "ordered"}], "the sofa that is closest to the television": [{"target_index": "6", "anchor_index": "5", "target_class": "sofa", "anchor_class": "television", "target_position": [1.646969569725383, 1.4343831838574637, -0.8058465123176575], "anchor_position": [2.4017462182100293, 3.6206627919874306, -0.45068351179361343], "target_colors": ["white", "white", "white"], "anchor_colors": ["black", "white", "N/A"], "target_size": 1.558315309492041, "anchor_size": 0.024298726093454417, "target_color_used": false, "target_size_used": false, "anchor_color_used": false, "anchor_size_used": false, "distractor_ids": ["0"], "relation": "closest", "relation_type": "ordered"}], "the sofa that is second closest to the television": [{"target_index": "0", "anchor_index": "5", "target_class": "sofa", "anchor_class": "television", "target_position": [-0.8847286519782817, 2.820139867313476, -0.8151715099811554], "anchor_position": [2.4017462182100293, 3.6206627919874306, -0.45068351179361343], "target_colors": ["white", "white", "white"], "anchor_colors": ["black", "white", "N/A"], "target_size": 1.3048886845010141, "anchor_size": 0.024298726093454417, "target_color_used": false, "target_size_used": false, "anchor_color_used": false, "anchor_size_used": false, "distractor_ids": ["6"], "relation": "closest", "relation_type": "ordered"}], "the sofa that is farthest from the small table": [{"target_index": "6", "anchor_index": "1", "target_class": "sofa", "anchor_class": "table", "target_position": [1.646969569725383, 1.4343831838574637, -0.8058465123176575], "anchor_position": [-0.628616208890724, 1.2396757955503994, -0.9589380025863647], "target_colors": ["white", "white", "white"], "anchor_colors": ["white", "white", "white"], "target_size": 1.558315309492041, "anchor_size": 0.05774846750669003, "target_color_used": false, "target_size_used": true, "anchor_color_used": false, "anchor_size_used": true, "distractor_ids": ["0"], "relation": "farthest", "relation_type": "ordered"}], "the sofa that is second farthest from the small table": [{"target_index": "0", "anchor_index": "1", "target_class": "sofa", "anchor_class": "table", "target_position": [-0.8847286519782817, 2.820139867313476, -0.8151715099811554], "anchor_position": [-0.628616208890724, 1.2396757955503994, -0.9589380025863647], "target_colors": ["white", "white", "white"], "anchor_colors": ["white", "white", "white"], "target_size": 1.3048886845010141, "anchor_size": 0.05774846750669003, "target_color_used": false, "target_size_used": true, "anchor_color_used": false, "anchor_size_used": true, "distractor_ids": ["6"], "relation": "farthest", "relation_type": "ordered"}], "the sofa that is farthest from the big table": [{"target_index": "6", "anchor_index": "2", "target_class": "sofa", "anchor_class": "table", "target_position": [1.646969569725383, 1.4343831838574637, -0.8058465123176575], "anchor_position": [-0.3500412798670293, 4.194660104284085, -0.8701274991035461], "target_colors": ["white", "white", "white"], "anchor_colors": ["white", "white", "white"], "target_size": 1.558315309492041, "anchor_size": 0.25376759151187633, "target_color_used": false, "target_size_used": true, "anchor_color_used": false, "anchor_size_used": true, "distractor_ids": ["0"], "relation": "farthest", "relation_type": "ordered"}], "the sofa that is second farthest from the big table": [{"target_index": "0", "anchor_index": "2", "target_class": "sofa", "anchor_class": "table", "target_position": [-0.8847286519782817, 2.820139867313476, -0.8151715099811554], "anchor_position": [-0.3500412798670293, 4.194660104284085, -0.8701274991035461], "target_colors": ["white", "white", "white"], "anchor_colors": ["white", "white", "white"], "target_size": 1.3048886845010141, "anchor_size": 0.25376759151187633, "target_color_used": false, "target_size_used": true, "anchor_color_used": false, "anchor_size_used": true, "distractor_ids": ["6"], "relation": "farthest", "relation_type": "ordered"}], "the sofa that is farthest from the black table": [{"target_index": "0", "anchor_index": "4", "target_class": "sofa", "anchor_class": "table", "target_position": [-0.8847286519782817, 2.820139867313476, -0.8151715099811554], "anchor_position": [2.3916712154017836, 3.666921674464924, -0.9619214832782745], "target_colors": ["white", "white", "white"], "anchor_colors": ["black", "white", "N/A"], "target_size": 1.3048886845010141, "anchor_size": 0.15684705036934382, "target_color_used": true, "target_size_used": false, "anchor_color_used": true, "anchor_size_used": false, "distractor_ids": ["6"], "relation": "farthest", "relation_type": "ordered"}], "the sofa that is second farthest from the black table": [{"target_index": "6", "anchor_index": "4", "target_class": "sofa", "anchor_class": "table", "target_position": [1.646969569725383, 1.4343831838574637, -0.8058465123176575], "anchor_position": [2.3916712154017836, 3.666921674464924, -0.9619214832782745], "target_colors": ["white", "white", "white"], "anchor_colors": ["black", "white", "N/A"], "target_size": 1.558315309492041, "anchor_size": 0.15684705036934382, "target_color_used": true, "target_size_used": false, "anchor_color_used": true, "anchor_size_used": false, "distractor_ids": ["0"], "relation": "farthest", "relation_type": "ordered"}], "the table that is farthest from the fireplace": [{"target_index": "1", "anchor_index": "3", "target_class": "table", "anchor_class": "fireplace", "target_position": [-0.628616208890724, 1.2396757955503994, -0.9589380025863647], "anchor_position": [1.0792443169216395, 3.7453244376919157, -0.6639344990253448], "target_colors": ["white", "white", "white"], "anchor_colors": ["white", "black", "white"], "target_size": 0.05774846750669003, "anchor_size": 0.6292661753359982, "target_color_used": false, "target_size_used": false, "anchor_color_used": false, "anchor_size_used": false, "distractor_ids": ["2", "4"], "relation": "farthest", "relation_type": "ordered"}], "the table that is second farthest from the fireplace": [{"target_index": "2", "anchor_index": "3", "target_class": "table", "anchor_class": "fireplace", "target_position": [-0.3500412798670293, 4.194660104284085, -0.8701274991035461], "anchor_position": [1.0792443169216395, 3.7453244376919157, -0.6639344990253448], "target_colors": ["white", "white", "white"], "anchor_colors": ["white", "black", "white"], "target_size": 0.25376759151187633, "anchor_size": 0.6292661753359982, "target_color_used": false, "target_size_used": false, "anchor_color_used": false, "anchor_size_used": false, "distractor_ids": ["1", "4"], "relation": "farthest", "relation_type": "ordered"}], "the table that is third farthest from the fireplace": [{"target_index": "4", "anchor_index": "3", "target_class": "table", "anchor_class": "fireplace", "target_position": [2.3916712154017836, 3.666921674464924, -0.9619214832782745], "anchor_position": [1.0792443169216395, 3.7453244376919157, -0.6639344990253448], "target_colors": ["black", "white", "N/A"], "anchor_colors": ["white", "black", "white"], "target_size": 0.15684705036934382, "anchor_size": 0.6292661753359982, "target_color_used": false, "target_size_used": false, "anchor_color_used": false, "anchor_size_used": false, "distractor_ids": ["1", "2"], "relation": "farthest", "relation_type": "ordered"}], "the sofa that is farthest from the fireplace": [{"target_index": "6", "anchor_index": "3", "target_class": "sofa", "anchor_class": "fireplace", "target_position": [1.646969569725383, 1.4343831838574637, -0.8058465123176575], "anchor_position": [1.0792443169216395, 3.7453244376919157, -0.6639344990253448], "target_colors": ["white", "white", "white"], "anchor_colors": ["white", "black", "white"], "target_size": 1.558315309492041, "anchor_size": 0.6292661753359982, "target_color_used": false, "target_size_used": false, "anchor_color_used": false, "anchor_size_used": false, "distractor_ids": ["0"], "relation": "farthest", "relation_type": "ordered"}], "the sofa that is second farthest from the fireplace": [{"target_index": "0", "anchor_index": "3", "target_class": "sofa", "anchor_class": "fireplace", "target_position": [-0.8847286519782817, 2.820139867313476, -0.8151715099811554], "anchor_position": [1.0792443169216395, 3.7453244376919157, -0.6639344990253448], "target_colors": ["white", "white", "white"], "anchor_colors": ["white", "black", "white"], "target_size": 1.3048886845010141, "anchor_size": 0.6292661753359982, "target_color_used": false, "target_size_used": false, "anchor_color_used": false, "anchor_size_used": false, "distractor_ids": ["6"], "relation": "farthest", "relation_type": "ordered"}], "the table that is farthest from the television": [{"target_index": "1", "anchor_index": "5", "target_class": "table", "anchor_class": "television", "target_position": [-0.628616208890724, 1.2396757955503994, -0.9589380025863647], "anchor_position": [2.4017462182100293, 3.6206627919874306, -0.45068351179361343], "target_colors": ["white", "white", "white"], "anchor_colors": ["black", "white", "N/A"], "target_size": 0.05774846750669003, "anchor_size": 0.024298726093454417, "target_color_used": false, "target_size_used": false, "anchor_color_used": false, "anchor_size_used": false, "distractor_ids": ["2", "4"], "relation": "farthest", "relation_type": "ordered"}], "the table that is second farthest from the television": [{"target_index": "2", "anchor_index": "5", "target_class": "table", "anchor_class": "television", "target_position": [-0.3500412798670293, 4.194660104284085, -0.8701274991035461], "anchor_position": [2.4017462182100293, 3.6206627919874306, -0.45068351179361343], "target_colors": ["white", "white", "white"], "anchor_colors": ["black", "white", "N/A"], "target_size": 0.25376759151187633, "anchor_size": 0.024298726093454417, "target_color_used": false, "target_size_used": false, "anchor_color_used": false, "anchor_size_used": false, "distractor_ids": ["1", "4"], "relation": "farthest", "relation_type": "ordered"}], "the table that is third farthest from the television": [{"target_index": "4", "anchor_index": "5", "target_class": "table", "anchor_class": "television", "target_position": [2.3916712154017836, 3.666921674464924, -0.9619214832782745], "anchor_position": [2.4017462182100293, 3.6206627919874306, -0.45068351179361343], "target_colors": ["black", "white", "N/A"], "anchor_colors": ["black", "white", "N/A"], "target_size": 0.15684705036934382, "anchor_size": 0.024298726093454417, "target_color_used": false, "target_size_used": false, "anchor_color_used": false, "anchor_size_used": false, "distractor_ids": ["1", "2"], "relation": "farthest", "relation_type": "ordered"}], "the sofa that is farthest from the television": [{"target_index": "0", "anchor_index": "5", "target_class": "sofa", "anchor_class": "television", "target_position": [-0.8847286519782817, 2.820139867313476, -0.8151715099811554], "anchor_position": [2.4017462182100293, 3.6206627919874306, -0.45068351179361343], "target_colors": ["white", "white", "white"], "anchor_colors": ["black", "white", "N/A"], "target_size": 1.3048886845010141, "anchor_size": 0.024298726093454417, "target_color_used": false, "target_size_used": false, "anchor_color_used": false, "anchor_size_used": false, "distractor_ids": ["6"], "relation": "farthest", "relation_type": "ordered"}], "the sofa that is second farthest from the television": [{"target_index": "6", "anchor_index": "5", "target_class": "sofa", "anchor_class": "television", "target_position": [1.646969569725383, 1.4343831838574637, -0.8058465123176575], "anchor_position": [2.4017462182100293, 3.6206627919874306, -0.45068351179361343], "target_colors": ["white", "white", "white"], "anchor_colors": ["black", "white", "N/A"], "target_size": 1.558315309492041, "anchor_size": 0.024298726093454417, "target_color_used": false, "target_size_used": false, "anchor_color_used": false, "anchor_size_used": false, "distractor_ids": ["0"], "relation": "farthest", "relation_type": "ordered"}], "the television that is near the table": [{"target_index": "5", "anchor_index": "4", "target_class": "television", "anchor_class": "table", "target_position": [2.4017462182100293, 3.6206627919874306, -0.45068351179361343], "anchor_position": [2.3916712154017836, 3.666921674464924, -0.9619214832782745], "target_colors": ["black", "white", "N/A"], "anchor_colors": ["black", "white", "N/A"], "target_size": 0.024298726093454417, "anchor_size": 0.15684705036934382, "target_color_used": false, "target_size_used": false, "anchor_color_used": false, "anchor_size_used": false, "distractor_ids": [], "relation": "near", "relation_type": "binary"}], "the table that is near the television": [{"target_index": "4", "anchor_index": "5", "target_class": "table", "anchor_class": "television", "target_position": [2.3916712154017836, 3.666921674464924, -0.9619214832782745], "anchor_position": [2.4017462182100293, 3.6206627919874306, -0.45068351179361343], "target_colors": ["black", "white", "N/A"], "anchor_colors": ["black", "white", "N/A"], "target_size": 0.15684705036934382, "anchor_size": 0.024298726093454417, "target_color_used": false, "target_size_used": false, "anchor_color_used": false, "anchor_size_used": false, "distractor_ids": [], "relation": "near", "relation_type": "binary"}], "the television that is on the table": [{"target_index": "5", "anchor_index": "4", "target_class": "television", "anchor_class": "table", "target_position": [2.4017462182100293, 3.6206627919874306, -0.45068351179361343], "anchor_position": [2.3916712154017836, 3.666921674464924, -0.9619214832782745], "target_colors": ["black", "white", "N/A"], "anchor_colors": ["black", "white", "N/A"], "target_size": 0.024298726093454417, "anchor_size": 0.15684705036934382, "target_color_used": false, "target_size_used": false, "anchor_color_used": false, "anchor_size_used": false, "distractor_ids": [], "relation": "on", "relation_type": "binary"}], "region": "47204840"}}}