{"0": {"door": ["0"], "ceiling": ["1", "122", "136", "172", "209", "223"], "plant": ["2", "16"], "shelves": ["4", "24"], "wall": ["5", "6", "7", "17", "25"], "kitchen island": ["8", "22"], "cabinet": ["9", "19", "35"], "picture": ["10", "31"], "oven": ["11", "20", "28"], "microwave": ["14", "30"], "counter": ["15", "27", "29", "32"], "refridgerator": ["18"], "stove": ["21"], "sink": ["33", "36"], "chair": ["34", "38", "39", "40"], "banister": ["37", "41"], "floor": ["42"]}, "1": {"window": ["43", "61"], "table": ["44"], "ceiling": ["45"], "chair": ["46", "59", "60", "62", "63", "64"], "picture": ["47", "48", "50", "54"], "heater": ["49"], "door": ["51", "57"], "wall": ["52"], "plant": ["53"], "floor": ["58", "194"]}, "2": {"floor": ["65"], "pillow": ["67", "74", "78", "80", "82", "83", "86"], "wall": ["68"], "picture": ["69", "71", "73"], "door": ["70"], "ceiling": ["72", "102"], "bed": ["75"], "curtain": ["76", "84"], "plant": ["77"], "keyboard": ["79"], "window": ["81"], "coffee table": ["87"]}, "3": {"floor": ["90"], "wall": ["91", "162"], "door": ["92"], "toilet": ["93"], "picture": ["94"], "mirror": ["95"], "towel": ["96"], "sink": ["97"], "ceiling": ["98"]}, "4": {"door": ["101", "103", "106", "108", "109"], "wall": ["104", "111", "113"], "picture": ["105"], "bed": ["110"], "excercise equipment": ["112", "114"], "floor": ["115"], "ceiling": ["314"], "lamp": ["323", "351"]}, "5": {"wall": ["116"], "ceiling": ["117"], "stairs": ["118", "391"], "banister": ["119", "218"], "floor": ["120", "228"]}, "6": {"toilet": ["123", "130"], "wall": ["124", "126", "127"], "door": ["125", "131", "145"], "floor": ["128"]}, "7": {"sink": ["12", "148", "152"], "wall": ["134", "138", "139", "140", "151", "154", "160", "165"], "door": ["137", "144", "150", "244"], "drawer": ["141", "166"], "plant": ["142", "158", "164"], "bench": ["143"], "towel": ["146", "163"], "shelves": ["149"], "picture": ["153"], "counter": ["155"], "bathtub": ["156"], "basket": ["157"], "cup": ["159"], "floor": ["167"], "floor mat": ["168"]}, "8": {"wall": ["169"], "toilet": ["170"], "sink": ["171"], "cabinet": ["174"], "door": ["176", "180", "204"], "shower curtain": ["177"], "towel": ["179", "189", "191"], "bathtub": ["181"], "picture": ["182"], "floor": ["184"], "window": ["186"], "garbage bin": ["187"]}, "9": {"wall": ["192", "195", "196", "200"], "bed": ["193"], "door": ["197", "198", "202", "220"], "table": ["199"], "bench": ["203"], "television": ["205"], "picture": ["206", "207"], "floor": ["208"], "ceiling": ["282"]}, "10": {"wall": ["210", "221"], "banister": ["211", "216"], "stairs": ["212"]}, "11": {"picture": ["219", "225", "227", "229", "231", "232", "233"], "door": ["224", "226"], "ceiling": ["396"]}, "12": {"wall": ["132", "234", "239"], "floor": ["235", "272"], "bed": ["236"], "ceiling": ["237", "264", "356"], "door": ["240", "248", "255"], "picture": ["241", "242", "246", "247", "256", "260"], "television": ["245"], "luggage": ["249", "252"], "night stand": ["250", "251"], "chair": ["254", "259"], "desk": ["261"], "table": ["262"], "ottoman": ["263"]}, "13": {"shelves": ["265"], "hanger": ["266", "267", "270"], "wall": ["269", "271"], "column": ["273"], "cabinet": ["274"], "door way": ["275"], "luggage": ["276"], "box": ["277", "281"], "table": ["278"], "picture": ["279"], "chair": ["280"]}, "14": {"wall": ["283", "284", "290", "294", "295", "299"], "towel": ["285", "308"], "floor": ["286"], "ceiling": ["287"], "sink": ["289"], "door": ["291", "296"], "counter": ["292"], "plant": ["293"], "mirror": ["297"], "toilet plunger": ["298"], "toilet": ["300"], "window": ["301", "304"], "paper": ["302"], "shower hose": ["303"], "dresser": ["306"], "garbage bin": ["307", "309"]}, "15": {"door": ["311", "321", "334", "335", "409"], "drawer": ["312"], "cabinet": ["313"], "wall": ["315", "344"], "sofa": ["317"], "picture": ["319", "326", "327", "329", "331", "337", "340"], "chair": ["322", "333"], "television": ["324"], "floor": ["325"], "table": ["330"], "plant": ["341"], "rug": ["353"]}, "16": {"floor": ["354"], "wall": ["355"], "playpen": ["357"], "sofa": ["359"], "computer": ["360"], "stool": ["364", "365", "369"], "door": ["366"], "sink": ["367"], "chair": ["370", "375"], "table": ["373", "374"]}, "17": {"ceiling": ["377"], "wall": ["378"], "sofa": ["380"], "door": ["381"], "towel": ["382"], "basket": ["383"], "table": ["385"], "pillow": ["386"], "plant": ["388"], "railing": ["389"], "floor": ["392"], "rug": ["393"]}, "18": {"wall": ["394", "400", "402", "403"], "floor": ["398"], "bench": ["399"], "picture": ["401", "405"], "door": ["404", "407", "408"]}}